[
    {
        "ott_launch_date": null,
        "auth_expiration_date": null,
        "tms_id": "",
        "description": "Never mess with a wulf's food.",
        "title_suggest": {
            "input": [
                "Mozzarella Sticks",
                "Sticks"
            ]
        },
        "title": "Mozzarella Sticks",
        "expiration_date": null,
        "type": "clip",
        "platforms": [
            "android",
            "fire-tv",
            "ios",
            "online-exclusive",
            "roku"
        ],
        "collection_id": "AWl9msNHAScUIg8XxeCA",
        "duration": 91.73,
        "original_air_date": null,
        "auth_launch_date": null,
        "clip_order": null,
        "media_id": "",
        "modified": 1553636977,
        "slug": "mozzarella-sticks",
        "exclude_from_search": false,
        "thumbnail": "https://i.cdn.turner.com/adultswim/big/image-upload/thumbnails/thumb-1_image-15536364121032.jpg",
        "created": 1553636972,
        "season_number": "",
        "title_id": "",
        "tv_rating": "",
        "blacklist": [],
        "ott_expiration_date": null,
        "published": 1553636977,
        "tags": [
            "lazor wulf",
            "sneak peek",
            "clip",
            "vince staples",
            "stupid horse",
            "cannon wulf",
            "adult swim"
        ],
        "collection_title": "Lazor Wulf",
        "modified_by": "Jared Marquez",
        "launch_date": 1554127200,
        "poster": "https://i.cdn.turner.com/adultswim/big/image-upload/thumbnails/thumb-2_image-15536364121032.jpg",
        "id": "AWm7-tk0AScUIg8XxeSY",
        "auth": false
    },
    {
        "ott_launch_date": null,
        "auth_expiration_date": null,
        "tms_id": "",
        "description": "Even God needs a holiday.",
        "title_suggest": {
            "input": [
                "No Chill",
                "Chill"
            ]
        },
        "title": "No Chill",
        "expiration_date": null,
        "type": "clip",
        "platforms": [
            "android",
            "fire-tv",
            "ios",
            "online-exclusive",
            "roku"
        ],
        "collection_id": "AWl9msNHAScUIg8XxeCA",
        "duration": 99.5,
        "original_air_date": null,
        "auth_launch_date": null,
        "clip_order": null,
        "media_id": "",
        "modified": 1553637065,
        "slug": "no-chill",
        "exclude_from_search": false,
        "thumbnail": "https://i.cdn.turner.com/adultswim/big/image-upload/thumbnails/thumb-1_image-155363699756116.jpg",
        "created": 1553637059,
        "season_number": "",
        "title_id": "",
        "tv_rating": "",
        "blacklist": [],
        "ott_expiration_date": null,
        "published": 1553637065,
        "tags": [
            "lazor wulf",
            "sneak peek",
            "clip",
            "vince staples",
            "god",
            "chill",
            "adult swim"
        ],
        "collection_title": "Lazor Wulf",
        "modified_by": "Jared Marquez",
        "launch_date": 1554696000,
        "poster": "https://i.cdn.turner.com/adultswim/big/image-upload/thumbnails/thumb-2_image-155363699756116.jpg",
        "id": "AWm7_C0sAScUIg8XxeSZ",
        "auth": false
    },
    {
        "ott_launch_date": null,
        "auth_expiration_date": null,
        "tms_id": "",
        "description": "RESPECT the cereal aisle.",
        "title_suggest": {
            "input": [
                "Cereal"
            ]
        },
        "title": "Cereal",
        "expiration_date": null,
        "type": "clip",
        "platforms": [
            "android",
            "fire-tv",
            "ios",
            "online-exclusive",
            "roku"
        ],
        "collection_id": "AWl9msNHAScUIg8XxeCA",
        "duration": 83.8,
        "original_air_date": null,
        "auth_launch_date": null,
        "clip_order": null,
        "media_id": "",
        "modified": 1553637142,
        "slug": "cereal",
        "exclude_from_search": false,
        "thumbnail": "https://i.cdn.turner.com/adultswim/big/image-upload/thumbnails/thumb-1_image-15536370843991.jpg",
        "created": 1553637115,
        "season_number": "",
        "title_id": "",
        "tv_rating": "",
        "blacklist": [],
        "ott_expiration_date": null,
        "published": 1553637142,
        "tags": [
            "lazor wulf",
            "sneak peek",
            "clip",
            "vince staples",
            "cereal",
            "karate kid",
            "adult swim"
        ],
        "collection_title": "Lazor Wulf",
        "modified_by": "Jared Marquez",
        "launch_date": 1555300800,
        "poster": "https://i.cdn.turner.com/adultswim/big/image-upload/thumbnails/thumb-2_image-15536370843991.jpg",
        "id": "AWm7_QeYAScUIg8XxeSa",
        "auth": false
    },
    {
        "ott_launch_date": null,
        "auth_expiration_date": null,
        "tms_id": "",
        "description": "Watch where you howl.",
        "title_suggest": {
            "input": [
                "Nice Ass Moon",
                "Ass Moon",
                "Moon"
            ]
        },
        "title": "Nice Ass Moon",
        "expiration_date": null,
        "type": "clip",
        "platforms": [
            "android",
            "fire-tv",
            "ios",
            "online-exclusive",
            "roku"
        ],
        "collection_id": "AWl9msNHAScUIg8XxeCA",
        "duration": 79.75,
        "original_air_date": null,
        "auth_launch_date": null,
        "clip_order": null,
        "media_id": "",
        "modified": 1555439443,
        "slug": "nice-ass-moon",
        "exclude_from_search": false,
        "thumbnail": "https://i.cdn.turner.com/adultswim/big/image-upload/thumbnails/thumb-1_image-155363736977711.jpg",
        "created": 1553637410,
        "season_number": "",
        "title_id": "",
        "tv_rating": "",
        "blacklist": [],
        "ott_expiration_date": null,
        "published": 1555439443,
        "tags": [
            "lazor wulf",
            "sneak peek",
            "clip",
            "vince staples",
            "moon",
            "adult swim"
        ],
        "collection_title": "Lazor Wulf",
        "modified_by": "Jared Marquez",
        "launch_date": 1555300800,
        "poster": "https://i.cdn.turner.com/adultswim/big/image-upload/thumbnails/thumb-2_image-155363736977711.jpg",
        "id": "AWm8AYZRAScUIg8XxeSf",
        "auth": false
    },
    {
        "ott_launch_date": null,
        "auth_expiration_date": null,
        "tms_id": "",
        "description": "Lazor Wulf wants change but no one cares.",
        "title_suggest": {
            "input": [
                "Pickles & Milk",
                "& Milk",
                "Milk"
            ]
        },
        "title": "Pickles & Milk",
        "expiration_date": null,
        "type": "clip",
        "platforms": [
            "android",
            "fire-tv",
            "ios",
            "online-exclusive",
            "roku"
        ],
        "collection_id": "AWl9msNHAScUIg8XxeCA",
        "duration": 89.13,
        "original_air_date": null,
        "auth_launch_date": null,
        "clip_order": null,
        "media_id": "",
        "modified": 1555439476,
        "slug": "pickles-milk",
        "exclude_from_search": false,
        "thumbnail": "https://i.cdn.turner.com/adultswim/big/image-upload/thumbnails/thumb-1_image-155363755695118.jpg",
        "created": 1553637586,
        "season_number": "",
        "title_id": "",
        "tv_rating": "",
        "blacklist": [],
        "ott_expiration_date": null,
        "published": 1555439476,
        "tags": [
            "lazor wulf",
            "sneak peek",
            "clip",
            "vince staples",
            "pickles",
            "milk",
            "adult swim"
        ],
        "collection_title": "Lazor Wulf",
        "modified_by": "Jared Marquez",
        "launch_date": 1555905600,
        "poster": "https://i.cdn.turner.com/adultswim/big/image-upload/thumbnails/thumb-2_image-155363755695118.jpg",
        "id": "AWm8BDaZAScUIg8XxeSh",
        "auth": false
    },
    {
        "ott_launch_date": null,
        "auth_expiration_date": null,
        "tms_id": "",
        "description": "War. What is it good for? Absolutely nothing.",
        "title_suggest": {
            "input": [
                "The Great Battle",
                "Great Battle",
                "Battle"
            ]
        },
        "title": "The Great Battle",
        "expiration_date": null,
        "type": "clip",
        "platforms": [
            "android",
            "fire-tv",
            "ios",
            "online-exclusive",
            "roku"
        ],
        "collection_id": "AWl9msNHAScUIg8XxeCA",
        "duration": 105.4,
        "original_air_date": null,
        "auth_launch_date": null,
        "clip_order": null,
        "media_id": "",
        "modified": 1555439515,
        "slug": "the-great-battle",
        "exclude_from_search": false,
        "thumbnail": "https://i.cdn.turner.com/adultswim/big/image-upload/thumbnails/thumb-1_image-155363764818912.jpg",
        "created": 1553637666,
        "season_number": "",
        "title_id": "",
        "tv_rating": "",
        "blacklist": [],
        "ott_expiration_date": null,
        "published": 1555439515,
        "tags": [
            "lazor wulf",
            "sneak peek",
            "clip",
            "vince staples",
            "stupid horse",
            "cannon horse",
            "adult swim"
        ],
        "collection_title": "Lazor Wulf",
        "modified_by": "Jared Marquez",
        "launch_date": 1555905600,
        "poster": "https://i.cdn.turner.com/adultswim/big/image-upload/thumbnails/thumb-2_image-155363764818912.jpg",
        "id": "AWm8BW_oAScUIg8XxeSi",
        "auth": false
    },
    {
        "ott_launch_date": 1554129000,
        "auth_expiration_date": 1615265940,
        "tms_id": "EP031867090002",
        "description": "That was today. This is tomorrow.",
        "title_suggest": {
            "input": [
                "That Was Today. This Is Tomorrow.",
                "Was Today. This Is Tomorrow.",
                "Today. This Is Tomorrow.",
                "This Is Tomorrow.",
                "Is Tomorrow.",
                "Tomorrow."
            ]
        },
        "title": "That Was Today. This Is Tomorrow.",
        "type": "episode",
        "expiration_date": 1617249540,
        "platforms": [
            "android",
            "fire-tv",
            "ios",
            "ott",
            "roku"
        ],
        "collection_id": "AWl9msNHAScUIg8XxeCA",
        "duration": 681.17,
        "episode_number": "2",
        "original_air_date": 1554696900,
        "auth_launch_date": 1612242000,
        "clip_order": null,
        "airing_id": "RADS1003032100078765",
        "media_id": "ef9074ee57cc14920f69e43dbfeca558a35dbf18",
        "modified": 1614839326,
        "slug": "that-was-today-this-is-tomorrow",
        "exclude_from_search": false,
        "thumbnail": "https://i.cdn.turner.com/adultswim/big/image-upload/thumbnails/thumb-1_image-155430974878612.jpg",
        "created": 1553916364,
        "title_id": "2178190",
        "season_number": "1",
        "tv_rating": "tv-14-lv",
        "blacklist": [],
        "ott_expiration_date": null,
        "published": 1614839326,
        "tags": [],
        "collection_title": "Lazor Wulf",
        "disable_ads": false,
        "modified_by": "ODT Listener",
        "launch_date": 1615266000,
        "poster": "https://i.cdn.turner.com/adultswim/big/image-upload/thumbnails/thumb-2_image-155430974878612.jpg",
        "id": "AWnMogXrHl5gR6828zAn",
        "auth": false
    },
    {
        "ott_launch_date": 1554733800,
        "auth_expiration_date": 1614661140,
        "tms_id": "EP031867090001",
        "description": "Dying to eat.",
        "title_suggest": {
            "input": [
                "Dying to Eat",
                "to Eat",
                "Eat"
            ]
        },
        "title": "Dying to Eat",
        "type": "episode",
        "expiration_date": 1617249540,
        "platforms": [
            "android",
            "fire-tv",
            "ios",
            "ott",
            "roku"
        ],
        "collection_id": "AWl9msNHAScUIg8XxeCA",
        "duration": 688.79,
        "episode_number": "1",
        "original_air_date": 1554696000,
        "auth_launch_date": 1611637200,
        "clip_order": null,
        "airing_id": "RADS1002272100077153",
        "media_id": "2ec99faa7ab522b19a7be93d7b1423afcc72c362",
        "modified": 1616511867,
        "slug": "dying-to-eat",
        "exclude_from_search": false,
        "thumbnail": "https://i.cdn.turner.com/adultswim/big/image-upload/thumbnails/thumb-1_image-15543096441134.jpg",
        "created": 1553916364,
        "title_id": "2178189",
        "season_number": "1",
        "tv_rating": "tv-14-dl",
        "blacklist": [],
        "ott_expiration_date": null,
        "published": 1616511867,
        "tags": [],
        "collection_title": "Lazor Wulf",
        "disable_ads": false,
        "modified_by": "ODT Listener",
        "launch_date": 1614661200,
        "poster": "https://i.cdn.turner.com/adultswim/big/image-upload/thumbnails/thumb-2_image-15543096441134.jpg",
        "id": "AWnMogXzHl5gR6828zAo",
        "auth": false
    },
    {
        "ott_launch_date": 1555338600,
        "auth_expiration_date": 1616471940,
        "tms_id": "EP031867090004",
        "description": "At the end of the day.",
        "title_suggest": {
            "input": [
                "At the End of the Day",
                "the End of the Day",
                "End of the Day",
                "of the Day",
                "the Day",
                "Day"
            ]
        },
        "title": "At the End of the Day",
        "type": "episode",
        "expiration_date": 1617249540,
        "platforms": [
            "android",
            "fire-tv",
            "ios",
            "ott",
            "roku"
        ],
        "collection_id": "AWl9msNHAScUIg8XxeCA",
        "duration": 678.63,
        "episode_number": "4",
        "original_air_date": 1555301700,
        "auth_launch_date": 1613451600,
        "clip_order": null,
        "airing_id": "RADS1003172100082695",
        "media_id": "80e34b029910a869e3faaf1eb4278db0bad75f2e",
        "modified": 1616511872,
        "slug": "at-the-end-of-the-day",
        "exclude_from_search": false,
        "thumbnail": "https://i.cdn.turner.com/adultswim/big/image-upload/thumbnails/thumb-1_image-15549925220073.jpg",
        "created": 1554574694,
        "title_id": "2178192",
        "season_number": "1",
        "tv_rating": "tv-14-dl",
        "blacklist": [],
        "ott_expiration_date": null,
        "published": 1616511872,
        "tags": [],
        "collection_title": "Lazor Wulf",
        "disable_ads": false,
        "modified_by": "ODT Listener",
        "launch_date": 1616472000,
        "poster": "https://i.cdn.turner.com/adultswim/big/image-upload/thumbnails/thumb-2_image-15549925220073.jpg",
        "id": "AWnz31nIHl5gR6828zHM",
        "auth": false
    },
    {
        "ott_launch_date": 1555338600,
        "auth_expiration_date": 1615867140,
        "tms_id": "EP031867090003",
        "description": "Lane occupied.",
        "title_suggest": {
            "input": [
                "Lane Occupied",
                "Occupied"
            ]
        },
        "title": "Lane Occupied",
        "type": "episode",
        "expiration_date": 1617249540,
        "platforms": [
            "android",
            "fire-tv",
            "ios",
            "ott",
            "roku"
        ],
        "collection_id": "AWl9msNHAScUIg8XxeCA",
        "duration": 674.71,
        "episode_number": "3",
        "original_air_date": 1555300800,
        "auth_launch_date": 1612846800,
        "clip_order": null,
        "airing_id": "RADS1003112100081817",
        "media_id": "b7865c1cdcc3be10dae332732f041835e9621025",
        "modified": 1615504720,
        "slug": "lane-occupied",
        "exclude_from_search": false,
        "thumbnail": "https://i.cdn.turner.com/adultswim/big/image-upload/thumbnails/thumb-1_image-155499246258618.jpg",
        "created": 1554574694,
        "title_id": "2178191",
        "season_number": "1",
        "tv_rating": "tv-14-dl",
        "blacklist": [],
        "ott_expiration_date": null,
        "published": 1615504720,
        "tags": [],
        "collection_title": "Lazor Wulf",
        "disable_ads": false,
        "modified_by": "ODT Listener",
        "launch_date": 1615867200,
        "poster": "https://i.cdn.turner.com/adultswim/big/image-upload/thumbnails/thumb-2_image-155499246258618.jpg",
        "id": "AWnz31nLAScUIg8Xxeni",
        "auth": false
    },
    {
        "ott_launch_date": null,
        "auth_expiration_date": null,
        "tms_id": "",
        "description": "Here's an actual sound cloud.",
        "title_suggest": {
            "input": [
                "Gillie Wet Foot",
                "Wet Foot",
                "Foot"
            ]
        },
        "title": "Gillie Wet Foot",
        "expiration_date": null,
        "type": "clip",
        "platforms": [
            "android",
            "fire-tv",
            "ios",
            "online-exclusive",
            "roku"
        ],
        "collection_id": "AWl9msNHAScUIg8XxeCA",
        "duration": 81.87,
        "original_air_date": null,
        "auth_launch_date": null,
        "clip_order": null,
        "media_id": "",
        "modified": 1555439551,
        "slug": "gillie-wet-foot",
        "exclude_from_search": false,
        "thumbnail": "https://i.cdn.turner.com/adultswim/big/image-upload/thumbnails/thumb-1_image-15554389721453.jpg",
        "created": 1555439006,
        "season_number": "",
        "title_id": "",
        "tv_rating": "",
        "blacklist": [],
        "ott_expiration_date": null,
        "published": 1555439551,
        "tags": [
            "lazor wulf",
            "sneak peek",
            "clip",
            "vince staples",
            "cloud",
            "god",
            "adult swim",
            "promo"
        ],
        "collection_title": "Lazor Wulf",
        "modified_by": "Jared Marquez",
        "launch_date": 1556510400,
        "poster": "https://i.cdn.turner.com/adultswim/big/image-upload/thumbnails/thumb-2_image-15554389721453.jpg",
        "id": "AWonY7GzAScUIg8Xxe7V",
        "auth": false
    },
    {
        "ott_launch_date": null,
        "auth_expiration_date": null,
        "tms_id": "",
        "description": "What a bargain.",
        "title_suggest": {
            "input": [
                "Action Jackson",
                "Jackson"
            ]
        },
        "title": "Action Jackson",
        "expiration_date": null,
        "type": "clip",
        "platforms": [
            "android",
            "fire-tv",
            "ios",
            "online-exclusive",
            "roku"
        ],
        "collection_id": "AWl9msNHAScUIg8XxeCA",
        "duration": 79.23,
        "original_air_date": null,
        "auth_launch_date": null,
        "clip_order": null,
        "media_id": "",
        "modified": 1555439563,
        "slug": "action-jackson",
        "exclude_from_search": false,
        "thumbnail": "https://i.cdn.turner.com/adultswim/big/image-upload/thumbnails/thumb-1_image-15554390967372.jpg",
        "created": 1555439234,
        "season_number": "",
        "title_id": "",
        "tv_rating": "",
        "blacklist": [],
        "ott_expiration_date": null,
        "published": 1555439563,
        "tags": [
            "lazor wulf",
            "sneak peek",
            "clip",
            "vince staples",
            "action jackson",
            "adult swim",
            "promo"
        ],
        "collection_title": "Lazor Wulf",
        "modified_by": "Jared Marquez",
        "launch_date": 1556510400,
        "poster": "https://i.cdn.turner.com/adultswim/big/image-upload/thumbnails/thumb-2_image-15554390967372.jpg",
        "id": "AWonZyyJAScUIg8Xxe7X",
        "auth": false
    },
    {
        "ott_launch_date": null,
        "auth_expiration_date": null,
        "tms_id": "",
        "description": "Yeah right, dude.",
        "title_suggest": {
            "input": [
                "Round Theory",
                "Theory"
            ]
        },
        "title": "Round Theory",
        "expiration_date": null,
        "type": "clip",
        "platforms": [
            "android",
            "fire-tv",
            "ios",
            "online-exclusive",
            "roku"
        ],
        "collection_id": "AWl9msNHAScUIg8XxeCA",
        "duration": 58.5,
        "original_air_date": null,
        "auth_launch_date": null,
        "clip_order": null,
        "media_id": "",
        "modified": 1555439575,
        "slug": "round-theory",
        "exclude_from_search": false,
        "thumbnail": "https://i.cdn.turner.com/adultswim/big/image-upload/thumbnails/thumb-1_image-15554392891021.jpg",
        "created": 1555439308,
        "season_number": "",
        "title_id": "",
        "tv_rating": "",
        "blacklist": [],
        "ott_expiration_date": null,
        "published": 1555439575,
        "tags": [
            "lazor wulf",
            "sneak peek",
            "clip",
            "vince staples",
            "round",
            "adult swim",
            "promo"
        ],
        "collection_title": "Lazor Wulf",
        "modified_by": "Jared Marquez",
        "launch_date": 1557115200,
        "poster": "https://i.cdn.turner.com/adultswim/big/image-upload/thumbnails/thumb-2_image-15554392891021.jpg",
        "id": "AWonaFBgHl5gR6828zQ7",
        "auth": false
    },
    {
        "ott_launch_date": null,
        "auth_expiration_date": null,
        "tms_id": "",
        "description": "Don't try this at home.",
        "title_suggest": {
            "input": [
                "Raccoon Burrito",
                "Burrito"
            ]
        },
        "title": "Raccoon Burrito",
        "expiration_date": null,
        "type": "clip",
        "platforms": [
            "android",
            "fire-tv",
            "ios",
            "online-exclusive",
            "roku"
        ],
        "collection_id": "AWl9msNHAScUIg8XxeCA",
        "duration": 78.2,
        "original_air_date": null,
        "auth_launch_date": null,
        "clip_order": null,
        "media_id": "",
        "modified": 1555439590,
        "slug": "raccoon-burrito",
        "exclude_from_search": false,
        "thumbnail": "https://i.cdn.turner.com/adultswim/big/image-upload/thumbnails/thumb-1_image-155543937004914.jpg",
        "created": 1555439410,
        "season_number": "",
        "title_id": "",
        "tv_rating": "",
        "blacklist": [],
        "ott_expiration_date": null,
        "published": 1555439590,
        "tags": [
            "lazor wulf",
            "sneak peek",
            "clip",
            "vince staples",
            "raccoon",
            "burrito",
            "adult swim",
            "promo"
        ],
        "collection_title": "Lazor Wulf",
        "modified_by": "Jared Marquez",
        "launch_date": 1557115200,
        "poster": "https://i.cdn.turner.com/adultswim/big/image-upload/thumbnails/thumb-2_image-155543937004914.jpg",
        "id": "AWonadyZHl5gR6828zQ8",
        "auth": false
    },
    {
        "ott_launch_date": 1555943400,
        "auth_expiration_date": 1617249540,
        "tms_id": "EP031867090006",
        "description": "Where you from?",
        "title_suggest": {
            "input": [
                "Where You From?",
                "You From?",
                "From?"
            ]
        },
        "title": "Where You From?",
        "type": "episode",
        "expiration_date": 1614661140,
        "platforms": [
            "android",
            "fire-tv",
            "ios",
            "ott",
            "roku"
        ],
        "collection_id": "AWl9msNHAScUIg8XxeCA",
        "duration": 681.17,
        "episode_number": "6",
        "original_air_date": 1555906500,
        "auth_launch_date": 1614661200,
        "clip_order": null,
        "airing_id": "RADS1002272100077160",
        "media_id": "a67c38a351bf49021f8b64e4e5118a247a1f3a4f",
        "modified": 1616511868,
        "slug": "where-you-from",
        "exclude_from_search": false,
        "thumbnail": "https://i.cdn.turner.com/adultswim/big/image-upload/thumbnails/thumb-1_image-155561093584715.jpg",
        "created": 1555598644,
        "title_id": "2178194",
        "season_number": "1",
        "tv_rating": "tv-14-l",
        "blacklist": [],
        "ott_expiration_date": null,
        "published": 1616511868,
        "tags": [],
        "collection_title": "Lazor Wulf",
        "disable_ads": false,
        "modified_by": "ODT Listener",
        "launch_date": 1611637200,
        "poster": "https://i.cdn.turner.com/adultswim/big/image-upload/thumbnails/thumb-2_image-155561093584715.jpg",
        "id": "AWow55ZdAScUIg8Xxe9I",
        "auth": true
    },
    {
        "ott_launch_date": 1555943400,
        "auth_expiration_date": 1617249540,
        "tms_id": "EP031867090005",
        "description": "We good!",
        "title_suggest": {
            "input": [
                "We GO0D!",
                "GO0D!"
            ]
        },
        "title": "We GO0D!",
        "expiration_date": 1614056340,
        "type": "episode",
        "platforms": [
            "android",
            "fire-tv",
            "ios",
            "ott",
            "roku"
        ],
        "collection_id": "AWl9msNHAScUIg8XxeCA",
        "duration": 685.88,
        "episode_number": "5",
        "original_air_date": 1555905600,
        "auth_launch_date": 1614056400,
        "clip_order": null,
        "media_id": "6e772801c20b73455428100ba2173f847cdf5587",
        "modified": 1614046288,
        "airing_id": "RADS1002172100074427",
        "slug": "we-go-0-d",
        "exclude_from_search": false,
        "thumbnail": "https://i.cdn.turner.com/adultswim/big/image-upload/thumbnails/thumb-1_image-15556108755692.jpg",
        "created": 1555610901,
        "season_number": "1",
        "title_id": "2178193",
        "tv_rating": "tv-14-dlv",
        "blacklist": [],
        "ott_expiration_date": null,
        "published": 1614046288,
        "tags": [],
        "collection_title": "Lazor Wulf",
        "disable_ads": false,
        "modified_by": "ODT Listener",
        "launch_date": 1611032400,
        "poster": "https://i.cdn.turner.com/adultswim/big/image-upload/thumbnails/thumb-2_image-15556108755692.jpg",
        "id": "AWoxopyyHl5gR6828zRk",
        "auth": true
    },
    {
        "ott_launch_date": 1556548200,
        "auth_expiration_date": 1617249540,
        "tms_id": "EP031867090008",
        "description": "Keep it moving.",
        "title_suggest": {
            "input": [
                "Keep It Moving",
                "It Moving",
                "Moving"
            ]
        },
        "title": "Keep It Moving",
        "type": "episode",
        "expiration_date": 1615867140,
        "platforms": [
            "android",
            "fire-tv",
            "ios",
            "ott",
            "roku"
        ],
        "collection_id": "AWl9msNHAScUIg8XxeCA",
        "duration": 669.46,
        "episode_number": "8",
        "original_air_date": 1556511300,
        "auth_launch_date": 1615867200,
        "clip_order": null,
        "airing_id": "RADS1003112100081831",
        "media_id": "7ec841eb060e7e55f016638d018776928522cdea",
        "modified": 1615507547,
        "slug": "keep-it-moving",
        "exclude_from_search": false,
        "thumbnail": "https://i.cdn.turner.com/adultswim/big/image-upload/thumbnails/thumb-1_image-15562178560269.jpg",
        "created": 1556031006,
        "title_id": "2178196",
        "season_number": "1",
        "tv_rating": "tv-14-l",
        "blacklist": [],
        "ott_expiration_date": null,
        "published": 1615507547,
        "tags": [],
        "collection_title": "Lazor Wulf",
        "disable_ads": false,
        "modified_by": "ODT Listener",
        "launch_date": 1612846800,
        "poster": "https://i.cdn.turner.com/adultswim/big/image-upload/thumbnails/thumb-2_image-15562178560269.jpg",
        "id": "AWpKrOe9AScUIg8XxfFe",
        "auth": true
    },
    {
        "ott_launch_date": 1556548200,
        "auth_expiration_date": 1617249540,
        "tms_id": "EP031867090007",
        "description": "Prolly for the best.",
        "title_suggest": {
            "input": [
                "Prolly for the Best",
                "for the Best",
                "the Best",
                "Best"
            ]
        },
        "title": "Prolly for the Best",
        "type": "episode",
        "expiration_date": 1615265940,
        "platforms": [
            "android",
            "fire-tv",
            "ios",
            "ott",
            "roku"
        ],
        "collection_id": "AWl9msNHAScUIg8XxeCA",
        "duration": 683.04,
        "episode_number": "7",
        "original_air_date": 1556510400,
        "auth_launch_date": 1615266000,
        "clip_order": null,
        "airing_id": "RADS1003032100078736",
        "media_id": "37d3fcdeae1684756cc885694a2e84397b37e28d",
        "modified": 1615368325,
        "slug": "prolly-for-the-best",
        "exclude_from_search": false,
        "thumbnail": "https://i.cdn.turner.com/adultswim/big/image-upload/thumbnails/thumb-1_image-15562178183946.jpg",
        "created": 1556128087,
        "title_id": "2178195",
        "season_number": "1",
        "tv_rating": "tv-14-dl",
        "blacklist": [],
        "ott_expiration_date": null,
        "published": 1615368325,
        "tags": [],
        "collection_title": "Lazor Wulf",
        "disable_ads": false,
        "modified_by": "ODT Listener",
        "launch_date": 1612242000,
        "poster": "https://i.cdn.turner.com/adultswim/big/image-upload/thumbnails/thumb-2_image-15562178183946.jpg",
        "id": "AWpQdjyMHl5gR6828zVH",
        "auth": true
    },
    {
        "ott_launch_date": 1557153000,
        "auth_expiration_date": 1617249540,
        "tms_id": "EP031867090009",
        "description": "They ain't know.",
        "title_suggest": {
            "input": [
                "They Ain't Know",
                "Ain't Know",
                "Know"
            ]
        },
        "title": "They Ain't Know",
        "type": "episode",
        "expiration_date": 1616471940,
        "platforms": [
            "android",
            "fire-tv",
            "ios",
            "ott",
            "roku"
        ],
        "collection_id": "AWl9msNHAScUIg8XxeCA",
        "duration": 690.58,
        "episode_number": "9",
        "original_air_date": 1557115200,
        "auth_launch_date": 1616472000,
        "clip_order": null,
        "airing_id": "RADS1003172100082688",
        "media_id": "494f03facfa99ef80766ad89c14e5b47964f9aa5",
        "modified": 1616511869,
        "slug": "they-aint-know",
        "exclude_from_search": false,
        "thumbnail": "https://i.cdn.turner.com/adultswim/big/image-upload/thumbnails/thumb-1_image-155681975288417.jpg",
        "created": 1556407447,
        "title_id": "2178197",
        "season_number": "1",
        "tv_rating": "tv-14-dls",
        "blacklist": [],
        "ott_expiration_date": null,
        "published": 1616511869,
        "tags": [],
        "collection_title": "Lazor Wulf",
        "disable_ads": false,
        "modified_by": "ODT Listener",
        "launch_date": 1613451600,
        "poster": "https://i.cdn.turner.com/adultswim/big/image-upload/thumbnails/thumb-2_image-155681975288417.jpg",
        "id": "AWphHO5SAScUIg8XxfQS",
        "auth": true
    },
    {
        "ott_launch_date": 1557153000,
        "auth_expiration_date": 1614056340,
        "tms_id": "EP031867090010",
        "description": "It is what it is.",
        "title_suggest": {
            "input": [
                "It Is What It Is",
                "Is What It Is",
                "What It Is",
                "It Is",
                "Is"
            ]
        },
        "title": "It Is What It Is",
        "type": "episode",
        "expiration_date": 1617249540,
        "platforms": [
            "android",
            "fire-tv",
            "ios",
            "ott",
            "roku"
        ],
        "collection_id": "AWl9msNHAScUIg8XxeCA",
        "duration": 659.63,
        "episode_number": "10",
        "original_air_date": 1557116100,
        "auth_launch_date": 1611032400,
        "clip_order": null,
        "airing_id": "RADS1001152100064012",
        "media_id": "e16eb859c0d1ef2ad8bee9749605b309636252fe",
        "modified": 1614046266,
        "slug": "it-is-what-it-is",
        "exclude_from_search": false,
        "thumbnail": "https://i.cdn.turner.com/adultswim/big/image-upload/thumbnails/thumb-1_image-155681985223916.jpg",
        "created": 1556651406,
        "title_id": "2178198",
        "season_number": "1",
        "tv_rating": "tv-14-dl",
        "blacklist": [],
        "ott_expiration_date": null,
        "published": 1614046266,
        "tags": [],
        "collection_title": "Lazor Wulf",
        "disable_ads": false,
        "modified_by": "ODT Listener",
        "launch_date": 1614056400,
        "poster": "https://i.cdn.turner.com/adultswim/big/image-upload/thumbnails/thumb-2_image-155681985223916.jpg",
        "id": "AWpvp3VKAScUIg8XxfVq",
        "auth": false
    },
    {
        "auth_expiration_date": 1616385540,
        "tms_id": "",
        "description": "Prolly for the Better?",
        "title_suggest": {
            "input": [
                "Prolly for the Better?",
                "for the Better?",
                "the Better?",
                "Better?"
            ]
        },
        "title": "Prolly for the Better?",
        "expiration_date": 1619409540,
        "type": "episode",
        "platforms": [
            "android",
            "ios",
            "roku",
            "fire-tv"
        ],
        "collection_id": "AWl9msNHAScUIg8XxeCA",
        "duration": 663.3961,
        "episode_number": "7",
        "original_air_date": "1609736400",
        "auth_launch_date": 1613365200,
        "clip_order": null,
        "airing_id": "RADS1003172100082651",
        "media_id": "1cfcc49ce8f934ac57201ff9a4db295da510b25b",
        "modified": 1616015714,
        "slug": "prolly-for-the-better",
        "exclude_from_search": false,
        "thumbnail": "https://media.cdn.adultswim.com/uploads/20201124/thumbnails/1_2011241042103-LazorWulf_207_dup-20201006_ProllyForBetter.jpg",
        "created": 1606232532,
        "season_number": "2",
        "title_id": "2224738",
        "tv_rating": "tv-14-l",
        "published": 1616015714,
        "tags": [],
        "collection_title": "Lazor Wulf",
        "disable_ads": false,
        "modified_by": "ODT Listener",
        "launch_date": 1616385600,
        "poster": "https://media.cdn.adultswim.com/uploads/20201124/thumbnails/2_2011241042103-LazorWulf_207_dup-20201006_ProllyForBetter.jpg",
        "id": "AXX662fabxpjZvbXYlcz",
        "auth": false
    },
    {
        "auth_expiration_date": 1616990340,
        "tms_id": "",
        "description": "Keep Going.",
        "title_suggest": {
            "input": [
                "Keep Going",
                "Going"
            ]
        },
        "title": "Keep Going",
        "expiration_date": 1620014340,
        "type": "episode",
        "platforms": [
            "android",
            "ios",
            "roku",
            "fire-tv"
        ],
        "collection_id": "AWl9msNHAScUIg8XxeCA",
        "duration": 675.6083,
        "episode_number": "8",
        "original_air_date": "1609737300",
        "auth_launch_date": 1613970000,
        "clip_order": null,
        "airing_id": "RADS1003252100084000",
        "media_id": "ed2ec2bc50a44c670755e8259103c389c7a923de",
        "modified": 1616641165,
        "slug": "keep-going",
        "exclude_from_search": false,
        "thumbnail": "https://media.cdn.adultswim.com/uploads/20201124/thumbnails/1_2011241042289-LazorWulf_208_dup-20201013_KeepGoing.jpg",
        "created": 1606232552,
        "season_number": "2",
        "title_id": "2224739",
        "tv_rating": "tv-14-l",
        "published": 1616641165,
        "tags": [],
        "collection_title": "Lazor Wulf",
        "disable_ads": false,
        "modified_by": "ODT Listener",
        "launch_date": 1616990400,
        "poster": "https://media.cdn.adultswim.com/uploads/20201124/thumbnails/2_2011241042289-LazorWulf_208_dup-20201013_KeepGoing.jpg",
        "id": "AXX667M6LyLQBOXK_Prk",
        "auth": false
    },
    {
        "auth_expiration_date": 1618804740,
        "tms_id": "EP031867090013",
        "description": "Still Dying to Eat.",
        "title_suggest": {
            "input": [
                "Still Dying to Eat",
                "Dying to Eat",
                "to Eat",
                "Eat"
            ]
        },
        "title": "Still Dying to Eat",
        "expiration_date": 1615780740,
        "type": "episode",
        "platforms": [
            "android",
            "ios",
            "roku",
            "fire-tv"
        ],
        "collection_id": "AWl9msNHAScUIg8XxeCA",
        "duration": 675.6416,
        "episode_number": "1",
        "original_air_date": "1607317200",
        "auth_launch_date": 1615780800,
        "clip_order": null,
        "airing_id": "RADS1003082100079680",
        "media_id": "7cc2503fb0ad9c6e4180ce36c3b7a50e574f6db8",
        "modified": 1616511866,
        "slug": "still-dying-to-eat",
        "exclude_from_search": false,
        "thumbnail": "https://media.cdn.adultswim.com/uploads/20201124/thumbnails/1_2011241038493-LazorWulf_201_dup-20200930_DyingToEat.jpg",
        "created": 1606232339,
        "season_number": "2",
        "title_id": "2224732",
        "tv_rating": "tv-14-dl",
        "published": 1616511866,
        "tags": [],
        "collection_title": "Lazor Wulf",
        "disable_ads": false,
        "modified_by": "ODT Listener",
        "launch_date": 1612760400,
        "poster": "https://media.cdn.adultswim.com/uploads/20201124/thumbnails/2_2011241038493-LazorWulf_201_dup-20200930_DyingToEat.jpg",
        "id": "AXX66HRKbxpjZvbXYlcx",
        "auth": true
    },
    {
        "auth_expiration_date": 1619409540,
        "tms_id": "EP031867090012",
        "description": "If That Was Tomorrow. This Is Today.",
        "title_suggest": {
            "input": [
                "If That Was Tomorrow. This Is Today.",
                "That Was Tomorrow. This Is Today.",
                "Was Tomorrow. This Is Today.",
                "Tomorrow. This Is Today.",
                "This Is Today.",
                "Is Today.",
                "Today."
            ]
        },
        "title": "If That Was Tomorrow. This Is Today.",
        "expiration_date": 1616385540,
        "type": "episode",
        "platforms": [
            "android",
            "ios",
            "roku",
            "fire-tv"
        ],
        "collection_id": "AWl9msNHAScUIg8XxeCA",
        "duration": 669.9359,
        "episode_number": "2",
        "original_air_date": "1607318100",
        "auth_launch_date": 1616385600,
        "clip_order": null,
        "airing_id": "RADS1003172100082641",
        "media_id": "cc2a2a92db92b3badb479bed5fc33aa76ef48ab9",
        "modified": 1616015716,
        "slug": "if-that-was-tomorrow-this-is-today",
        "exclude_from_search": false,
        "thumbnail": "https://media.cdn.adultswim.com/uploads/20201124/thumbnails/1_2011241039145-LazorWulf_202_dup-20200930_IfThatWasTomorrow.jpg",
        "created": 1606232361,
        "season_number": "2",
        "title_id": "2224733",
        "tv_rating": "tv-14-l",
        "published": 1616015716,
        "tags": [],
        "collection_title": "Lazor Wulf",
        "disable_ads": false,
        "modified_by": "ODT Listener",
        "launch_date": 1613365200,
        "poster": "https://media.cdn.adultswim.com/uploads/20201124/thumbnails/2_2011241039145-LazorWulf_202_dup-20200930_IfThatWasTomorrow.jpg",
        "id": "AXX66MmlLyLQBOXK_Prg",
        "auth": true
    },
    {
        "auth_expiration_date": 1620014340,
        "tms_id": "EP031867090011",
        "description": "Unoccupied Lane.",
        "title_suggest": {
            "input": [
                "Unoccupied Lane",
                "Lane"
            ]
        },
        "title": "Unoccupied Lane",
        "expiration_date": 1616990340,
        "type": "episode",
        "platforms": [
            "android",
            "ios",
            "roku",
            "fire-tv"
        ],
        "collection_id": "AWl9msNHAScUIg8XxeCA",
        "duration": 666.299,
        "episode_number": "3",
        "original_air_date": "1585721700",
        "auth_launch_date": 1616990400,
        "clip_order": null,
        "airing_id": "RADS1002172100074371",
        "media_id": "938ea4661874978330ffb86220ff2057ec797d21",
        "modified": 1616636068,
        "slug": "unoccupied-lane",
        "exclude_from_search": false,
        "thumbnail": "https://media.cdn.adultswim.com/uploads/20201124/thumbnails/1_2011241039447-LazorWulf_203_dup-20200930_UnoccupiedLane.jpg",
        "created": 1606232387,
        "season_number": "2",
        "title_id": "2224734",
        "tv_rating": "tv-14-dlv",
        "published": 1616636068,
        "tags": [],
        "collection_title": "Lazor Wulf",
        "disable_ads": false,
        "modified_by": "ODT Listener",
        "launch_date": 1613970000,
        "poster": "https://media.cdn.adultswim.com/uploads/20201124/thumbnails/2_2011241039447-LazorWulf_203_dup-20200930_UnoccupiedLane.jpg",
        "id": "AXX66TF6LyLQBOXK_Prh",
        "auth": true
    },
    {
        "auth_expiration_date": 1614574740,
        "tms_id": "",
        "description": "The End Is High.",
        "title_suggest": {
            "input": [
                "The End Is High",
                "End Is High",
                "Is High",
                "High"
            ]
        },
        "title": "The End Is High",
        "expiration_date": 1617595140,
        "type": "episode",
        "platforms": [
            "android",
            "ios",
            "roku",
            "fire-tv"
        ],
        "collection_id": "AWl9msNHAScUIg8XxeCA",
        "duration": 652.9857,
        "episode_number": "4",
        "original_air_date": "1607922900",
        "auth_launch_date": 1612155600,
        "clip_order": null,
        "airing_id": "RADS1001292100069433",
        "media_id": "fdf38943fdbd4cfe8f6a02699c30d1f15b9e1c29",
        "modified": 1614390751,
        "slug": "the-end-is-high",
        "exclude_from_search": false,
        "thumbnail": "https://media.cdn.adultswim.com/uploads/20201124/thumbnails/1_2011241040101-LazorWulf_204_dup-20201001_EndIsHigh.jpg",
        "created": 1606232413,
        "season_number": "2",
        "title_id": "2224735",
        "tv_rating": "tv-14-l",
        "published": 1614390751,
        "tags": [],
        "collection_title": "Lazor Wulf",
        "disable_ads": false,
        "modified_by": "ODT Listener",
        "launch_date": 1614574800,
        "poster": "https://media.cdn.adultswim.com/uploads/20201124/thumbnails/2_2011241040101-LazorWulf_204_dup-20201001_EndIsHigh.jpg",
        "id": "AXX66ZR8LyLQBOXK_Pri",
        "auth": false
    },
    {
        "auth_expiration_date": 1617595140,
        "tms_id": "",
        "description": "They Knew.",
        "title_suggest": {
            "input": [
                "They Knew",
                "Knew"
            ]
        },
        "title": "They Knew",
        "expiration_date": 1614574740,
        "type": "episode",
        "platforms": [
            "android",
            "ios",
            "roku",
            "fire-tv"
        ],
        "collection_id": "AWl9msNHAScUIg8XxeCA",
        "duration": 669.8025,
        "episode_number": "9",
        "original_air_date": null,
        "auth_launch_date": 1614574800,
        "clip_order": null,
        "airing_id": "RADS1002272100077096",
        "media_id": "3ecfd5ef377e3193d4d6e3b2fdb5ba2ac156b7c4",
        "modified": 1614390445,
        "slug": "they-knew",
        "exclude_from_search": false,
        "thumbnail": "https://media.cdn.adultswim.com/uploads/20201124/thumbnails/1_2011241042464-LazorWulf_209_dup-20201013_TheyKnew.jpg",
        "created": 1606232569,
        "season_number": "2",
        "title_id": "2224740",
        "tv_rating": "tv-14-dl",
        "published": 1614390445,
        "tags": [],
        "collection_title": "Lazor Wulf",
        "disable_ads": false,
        "modified_by": "ODT Listener",
        "launch_date": 1612155600,
        "poster": "https://media.cdn.adultswim.com/uploads/20201124/thumbnails/2_2011241042464-LazorWulf_209_dup-20201013_TheyKnew.jpg",
        "id": "AXX66_gibxpjZvbXYlc0",
        "auth": true
    },
    {
        "auth_expiration_date": 1615179540,
        "tms_id": "",
        "description": "We Good?",
        "title_suggest": {
            "input": [
                "We Good?",
                "Good?"
            ]
        },
        "title": "We Good?",
        "expiration_date": 1618199940,
        "type": "episode",
        "platforms": [
            "android",
            "ios",
            "roku",
            "fire-tv"
        ],
        "collection_id": "AWl9msNHAScUIg8XxeCA",
        "duration": 674.2402,
        "episode_number": "5",
        "original_air_date": "1608526800",
        "auth_launch_date": 1612155600,
        "clip_order": null,
        "airing_id": "RADS1001292100069432",
        "media_id": "e13d911d014f84eb5dd801beec31b1a91c442c11",
        "modified": 1614814385,
        "slug": "we-good",
        "exclude_from_search": false,
        "thumbnail": "https://media.cdn.adultswim.com/uploads/20201124/thumbnails/1_2011241040363-LazorWulf_205_dup-20201001_WeGood.jpg",
        "created": 1606232454,
        "season_number": "2",
        "title_id": "2224736",
        "tv_rating": "tv-14-dl",
        "published": 1614814385,
        "tags": [],
        "collection_title": "Lazor Wulf",
        "disable_ads": false,
        "modified_by": "ODT Listener",
        "launch_date": 1615179600,
        "poster": "https://media.cdn.adultswim.com/uploads/20201124/thumbnails/2_2011241040363-LazorWulf_205_dup-20201001_WeGood.jpg",
        "id": "AXX66jaWbxpjZvbXYlcy",
        "auth": false
    },
    {
        "auth_expiration_date": 1615780740,
        "tms_id": "",
        "description": "Where You Stay?",
        "title_suggest": {
            "input": [
                "Where You Stay?",
                "You Stay?",
                "Stay?"
            ]
        },
        "title": "Where You Stay?",
        "expiration_date": 1618804740,
        "type": "episode",
        "platforms": [
            "android",
            "ios",
            "roku",
            "fire-tv"
        ],
        "collection_id": "AWl9msNHAScUIg8XxeCA",
        "duration": 672.305,
        "episode_number": "6",
        "original_air_date": "1608527700",
        "auth_launch_date": 1612760400,
        "clip_order": null,
        "airing_id": "RADS1003082100079662",
        "media_id": "88a7157aad46a36272bb65f34d544a6bd0799ae8",
        "modified": 1615358026,
        "slug": "where-you-stay",
        "exclude_from_search": false,
        "thumbnail": "https://media.cdn.adultswim.com/uploads/20201124/thumbnails/1_2011241041241-LazorWulf_206_dup-20201005_WhereYouStay.jpg",
        "created": 1606232506,
        "season_number": "2",
        "title_id": "2224737",
        "tv_rating": "tv-14-l",
        "published": 1615358026,
        "tags": [],
        "collection_title": "Lazor Wulf",
        "disable_ads": false,
        "modified_by": "ODT Listener",
        "launch_date": 1615780800,
        "poster": "https://media.cdn.adultswim.com/uploads/20201124/thumbnails/2_2011241041241-LazorWulf_206_dup-20201005_WhereYouStay.jpg",
        "id": "AXX66wHGLyLQBOXK_Prj",
        "auth": false
    },
    {
        "auth_expiration_date": 1618199940,
        "tms_id": "",
        "description": "Is It Tho?",
        "title_suggest": {
            "input": [
                "Is It Tho?",
                "It Tho?",
                "Tho?"
            ]
        },
        "title": "Is It Tho?",
        "expiration_date": 1615179540,
        "type": "episode",
        "platforms": [
            "android",
            "ios",
            "roku",
            "fire-tv"
        ],
        "collection_id": "AWl9msNHAScUIg8XxeCA",
        "duration": 659.3253,
        "episode_number": "10",
        "original_air_date": null,
        "auth_launch_date": 1615179600,
        "clip_order": null,
        "airing_id": "RADS1001292100069493",
        "media_id": "79838fe917d092bd24b7a2922dcf16f5b77e7a08",
        "modified": 1614813475,
        "slug": "is-it-tho",
        "exclude_from_search": false,
        "thumbnail": "https://media.cdn.adultswim.com/uploads/20201124/thumbnails/1_201124104303-LazorWulf_210_dup-20201021_IsItTho.jpg",
        "created": 1606232582,
        "season_number": "2",
        "title_id": "2224741",
        "tv_rating": "tv-14-dl",
        "published": 1614813475,
        "tags": [],
        "collection_title": "Lazor Wulf",
        "disable_ads": false,
        "modified_by": "ODT Listener",
        "launch_date": 1612156500,
        "poster": "https://media.cdn.adultswim.com/uploads/20201124/thumbnails/2_201124104303-LazorWulf_210_dup-20201021_IsItTho.jpg",
        "id": "AXX67Ci9LyLQBOXK_Prl",
        "auth": true
    }
]