[
    {
        "auth": true,
        "auth_expiration_date": 1663473540,
        "tms_id": "EP002070020091",
        "description": "As Thanksgiving approaches, Redcorn attempts to reestablish his relationship with Joseph; Bobby rejects the holiday; Peggy invents her own game.",
        "title_suggest": {
            "input": [
                "Spin the Choice",
                "the Choice",
                "Choice"
            ]
        },
        "title": "Spin the Choice",
        "type": "episode",
        "expiration_date": 1504443599,
        "platforms": [
            "web",
            "mobile"
        ],
        "collection_id": "zXXZkvdrRAa-8Cz4AV4QlA",
        "duration": 1400.5325,
        "episode_number": "4",
        "original_air_date": 1232420400,
        "auth_launch_date": 1662868800,
        "modified": 1662617514,
        "media_id": "3176ccdf0d074809c3b2fad89e151e92242e6baa",
        "airing_id": "RADS1009082200026163",
        "id": "4Yzvo_whTrC18scwPz5LtA",
        "slug": "spin-the-choice",
        "views": 4619,
        "created": 1417144828,
        "title_id": "731331",
        "tv_rating": "tv-pg",
        "season_number": "5",
        "published": 1662617514,
        "first_published": 1417144828,
        "tags": [],
        "collection_title": "King of the Hill",
        "modified_by": "ODT Listener",
        "launch_date": 1503838800,
        "cma_id": "1460470"
    },
    {
        "auth": true,
        "ott_launch_date": null,
        "auth_expiration_date": 1663214340,
        "tms_id": "EP002070020088",
        "rating": 8.080646,
        "description": "As election day approaches...Hank has second thoughts about voting for George W. Bush; Luanne supports a Communist.",
        "title_suggest": {
            "input": [
                "The Perils of Polling",
                "Perils of Polling",
                "of Polling",
                "Polling"
            ]
        },
        "type": "episode",
        "title": "The Perils of Polling",
        "expiration_date": 1504236599,
        "platforms": [
            "web",
            "mobile"
        ],
        "collection_id": "zXXZkvdrRAa-8Cz4AV4QlA",
        "duration": 1399.765,
        "episode_number": "1",
        "original_air_date": 1232249400,
        "auth_launch_date": 1662609600,
        "clip_order": null,
        "modified": 1662558387,
        "media_id": "979fe3253b655d8e187c3d973bf6c0fee71b57b2",
        "airing_id": "RADS1009022200025979",
        "id": "ImZdlO9DTBagX5EjRavXvQ",
        "slug": "the-perils-of-polling",
        "views": 274428,
        "exclude_from_search": false,
        "thumbnail": "https://media.cdn.adultswim.com/uploads/20220906/thumbnails/1_22961355440-KingOfTheHill_502_ThePerilsOfPolling.png",
        "created": 1402945468,
        "title_id": "731328",
        "season_number": "5",
        "tv_rating": "tv-pg-dl",
        "active": false,
        "blacklist": [],
        "ott_expiration_date": null,
        "published": 1662558387,
        "tags": [
            "the perils of polling",
            " election day",
            " hank",
            " george w bush",
            " luanne",
            " vote",
            " communist"
        ],
        "rating_count": 310,
        "collection_title": "King of the Hill",
        "disable_ads": false,
        "modified_by": "Jonas Eason",
        "launch_date": 1503631800,
        "poster": "https://media.cdn.adultswim.com/uploads/20220906/thumbnails/2_22961355440-KingOfTheHill_502_ThePerilsOfPolling.png",
        "cma_id": "1459326"
    },
    {
        "auth": true,
        "ott_launch_date": null,
        "auth_expiration_date": 1663387140,
        "tms_id": "EP002070020090",
        "rating": 8.959594,
        "description": "\"...for Our Lives To Be Over, I Want To Know...\" A rift develops between Bobby and Joseph when Joseph returns from summer camp very much a man; Hank builds coffins for his family.",
        "title_suggest": {
            "input": [
                "I Don't Want to Wait...",
                "Don't Want to Wait...",
                "Want to Wait...",
                "to Wait...",
                "Wait..."
            ]
        },
        "type": "episode",
        "title": "I Don't Want to Wait...",
        "expiration_date": 1504441799,
        "platforms": [
            "web",
            "mobile"
        ],
        "collection_id": "zXXZkvdrRAa-8Cz4AV4QlA",
        "duration": 1397.1958,
        "episode_number": "3",
        "original_air_date": 1241316000,
        "auth_launch_date": 1662782400,
        "clip_order": null,
        "modified": 1662613853,
        "media_id": "3050b138315ded66dc78da3bb76a01327b148172",
        "airing_id": "RADS1009082200026124",
        "id": "VVeBjxGgSp6b4ciWJLleIQ",
        "slug": "i-dont-want-to-wait",
        "views": 105892,
        "thumbnail": "https://i.cdn.turner.com/adultswim/big/image-upload/thumbnails/thumb-1_image-151931835778212.jpg",
        "created": 1402945468,
        "title_id": "731330",
        "season_number": "5",
        "tv_rating": "tv-pg",
        "active": false,
        "blacklist": [],
        "ott_expiration_date": null,
        "published": 1662613853,
        "tags": [
            "I Don't Want to Wait for Our Lives To Be Over",
            " I Want To Know",
            " King of the Hill",
            " Adult Swim",
            " video",
            " funny",
            " Mike Judge",
            " Hank",
            " Peggy",
            " Bobby"
        ],
        "rating_count": 99,
        "collection_title": "King of the Hill",
        "modified_by": "ODT Listener",
        "launch_date": 1503837000,
        "poster": "https://i.cdn.turner.com/adultswim/big/image-upload/thumbnails/thumb-2_image-151931835778212.jpg",
        "cma_id": "1460512"
    },
    {
        "auth": true,
        "auth_expiration_date": 1663127940,
        "tms_id": "EP002070020087",
        "rating": 7.9672127,
        "description": "During a trip to Nashville, Peggy accuses Randy Travis of stealing a song she wrote.",
        "title_suggest": {
            "input": [
                "Peggy's Fan Fair",
                "Fan Fair",
                "Fair"
            ]
        },
        "type": "episode",
        "title": "Peggy's Fan Fair",
        "expiration_date": 1504150199,
        "platforms": [
            "web",
            "mobile"
        ],
        "collection_id": "zXXZkvdrRAa-8Cz4AV4QlA",
        "duration": 1403.3019,
        "episode_number": "24",
        "original_air_date": 1241231400,
        "auth_launch_date": 1662523200,
        "clip_order": null,
        "modified": 1662486897,
        "media_id": "4caf7f7c01ac6082e38c97f70082cbc71ab76bb0",
        "airing_id": "RADS1009022200025853",
        "id": "dZ1mQdcjQCqTwTOC4UOCYA",
        "slug": "peggys-fan-fair",
        "views": 184257,
        "exclude_from_search": false,
        "thumbnail": "https://media.cdn.adultswim.com/uploads/20220906/thumbnails/1_22961354345-KingOfTheHill_423_PeggysFanFair.png",
        "created": 1402945468,
        "title_id": "731327",
        "season_number": "4",
        "tv_rating": "tv-pg",
        "active": false,
        "published": 1662486897,
        "tags": [
            "King of the Hill Episode 423 Peggy's fan fare"
        ],
        "rating_count": 244,
        "collection_title": "King of the Hill",
        "disable_ads": false,
        "modified_by": "Sara Griggs",
        "launch_date": 1503545400,
        "poster": "https://media.cdn.adultswim.com/uploads/20220906/thumbnails/2_22961354345-KingOfTheHill_423_PeggysFanFair.png",
        "cma_id": "1458825"
    },
    {
        "auth": true,
        "auth_expiration_date": 1663300740,
        "tms_id": "EP002070020089",
        "rating": 8.146106,
        "description": "When Bobby begins caddying for Buck Strickland, some of Buck's bad habits rub off on the boy...much to Hank's dismay.",
        "title_suggest": {
            "input": [
                "The Buck Stops Here",
                "Buck Stops Here",
                "Stops Here",
                "Here"
            ]
        },
        "type": "episode",
        "title": "The Buck Stops Here",
        "expiration_date": 1504322999,
        "platforms": [
            "web",
            "mobile"
        ],
        "collection_id": "zXXZkvdrRAa-8Cz4AV4QlA",
        "duration": 1397.1958,
        "episode_number": "2",
        "original_air_date": 1232247600,
        "auth_launch_date": 1662696000,
        "clip_order": null,
        "modified": 1662487039,
        "media_id": "4a1297517fa184ca789bb8cdf582f9e4d1174de7",
        "airing_id": "RADS1009022200025891",
        "id": "mwZsU2_oShCXRPmFupVQOg",
        "slug": "the-buck-stops-here",
        "views": 292467,
        "exclude_from_search": false,
        "thumbnail": "https://media.cdn.adultswim.com/uploads/20220906/thumbnails/1_22961356557-KingOfTheHill_501_TheBuckStopsHere.png",
        "created": 1402945468,
        "title_id": "731329",
        "season_number": "5",
        "tv_rating": "tv-pg-dl",
        "active": false,
        "published": 1662487039,
        "tags": [
            "the buck stops here",
            " bobby",
            " caddy",
            " buck strickland",
            " bad habits",
            " boy",
            " hank",
            " dismay"
        ],
        "rating_count": 308,
        "collection_title": "King of the Hill",
        "disable_ads": false,
        "modified_by": "Sara Griggs",
        "launch_date": 1503718200,
        "poster": "https://media.cdn.adultswim.com/uploads/20220906/thumbnails/2_22961356557-KingOfTheHill_501_TheBuckStopsHere.png",
        "cma_id": "1459650"
    }
]